XiangIdeYiyangShiyongVim/README.md
XiangIdeYiyangShiyongVim/__init__.py
XiangIdeYiyangShiyongVim/__main__.py
XiangIdeYiyangShiyongVim/file.epub
XiangIdeYiyangShiyongVim/index.html
XiangIdeYiyangShiyongVim/css/__init__.py
XiangIdeYiyangShiyongVim/css/annotations.css
XiangIdeYiyangShiyongVim/css/main.css
XiangIdeYiyangShiyongVim/css/normalize.css
XiangIdeYiyangShiyongVim/css/popup.css
XiangIdeYiyangShiyongVim/font/__init__.py
XiangIdeYiyangShiyongVim/font/fontello.eot
XiangIdeYiyangShiyongVim/font/fontello.svg
XiangIdeYiyangShiyongVim/font/fontello.ttf
XiangIdeYiyangShiyongVim/font/fontello.woff
XiangIdeYiyangShiyongVim/img/__init__.py
XiangIdeYiyangShiyongVim/img/annotator-glyph-sprite.png
XiangIdeYiyangShiyongVim/img/annotator-icon-sprite.png
XiangIdeYiyangShiyongVim/img/apple-touch-icon.png
XiangIdeYiyangShiyongVim/img/cancelfullscreen.png
XiangIdeYiyangShiyongVim/img/close.png
XiangIdeYiyangShiyongVim/img/fullscreen.png
XiangIdeYiyangShiyongVim/img/loader.gif
XiangIdeYiyangShiyongVim/img/menu-icon.png
XiangIdeYiyangShiyongVim/img/save.png
XiangIdeYiyangShiyongVim/img/saved.png
XiangIdeYiyangShiyongVim/img/settings-s.png
XiangIdeYiyangShiyongVim/img/settings.png
XiangIdeYiyangShiyongVim/img/star.png
XiangIdeYiyangShiyongVim/js/__init__.py
XiangIdeYiyangShiyongVim/js/epub.js
XiangIdeYiyangShiyongVim/js/epub.min.js
XiangIdeYiyangShiyongVim/js/epub.min.map
XiangIdeYiyangShiyongVim/js/hooks.min.js
XiangIdeYiyangShiyongVim/js/hooks.min.map
XiangIdeYiyangShiyongVim/js/reader.js
XiangIdeYiyangShiyongVim/js/reader.js.map
XiangIdeYiyangShiyongVim/js/reader.min.js
XiangIdeYiyangShiyongVim/js/reader.min.map
XiangIdeYiyangShiyongVim/js/hooks/__init__.py
XiangIdeYiyangShiyongVim/js/hooks/extensions/__init__.py
XiangIdeYiyangShiyongVim/js/hooks/extensions/highlight.js
XiangIdeYiyangShiyongVim/js/libs/__init__.py
XiangIdeYiyangShiyongVim/js/libs/jquery.min.js
XiangIdeYiyangShiyongVim/js/libs/localforage.min.js
XiangIdeYiyangShiyongVim/js/libs/screenfull.js
xiang_ide_yiyang_shiyong_vim-2024.2.29.0.dist-info/METADATA
xiang_ide_yiyang_shiyong_vim-2024.2.29.0.dist-info/WHEEL
xiang_ide_yiyang_shiyong_vim-2024.2.29.0.dist-info/entry_points.txt
xiang_ide_yiyang_shiyong_vim-2024.2.29.0.dist-info/top_level.txt
xiang_ide_yiyang_shiyong_vim-2024.2.29.0.dist-info/RECORD
